datamedic/__init__.py
datamedic/cleaner.py
datamedic/cli.py
datamedic/eda.py
datamedic/encoder.py
datamedic/leakage.py
datamedic/pca.py
datamedic/scaler.py
datamedic-1.0.0.post1.dist-info/METADATA
datamedic-1.0.0.post1.dist-info/WHEEL
datamedic-1.0.0.post1.dist-info/entry_points.txt
datamedic-1.0.0.post1.dist-info/top_level.txt
datamedic-1.0.0.post1.dist-info/RECORD
