Metadata-Version: 2.4
Name: datamedic
Version: 1.0.0.post1
Summary: A Python package for cleaning CSV files and detecting data leakage in machine learning workflows
Author-email: Ansh Malik <anshmalik845@gmail.com>
Project-URL: Documentation, https://drive.google.com/file/d/1-C_I3NhjZ3CU0YQJlsGxmixaG7iJOqUw/view?usp=sharing
Project-URL: Demo Video, https://drive.google.com/file/d/1cPiCC2rxUh0GD3RMAYj0QTJURQK7MQnH/view?usp=sharing
Project-URL: Linktree, https://linktr.ee/AnshM845
Classifier: Programming Language :: Python :: 3
Classifier: License :: OSI Approved :: MIT License
Classifier: Operating System :: OS Independent
Classifier: Intended Audience :: Developers
Classifier: Topic :: Software Development :: Libraries
Classifier: Topic :: Scientific/Engineering :: Information Analysis
Requires-Python: >=3.8
Requires-Dist: click>=8.1.3
Requires-Dist: pandas>=1.5.3
Requires-Dist: scikit-learn>=1.2.2
Requires-Dist: numpy>=1.24.3
Requires-Dist: matplotlib>=3.7.1
Requires-Dist: seaborn>=0.12.2
